xploitv/__init__.py
xploitv/__main__.py
xploitv/arguments.py
xploitv/grabber.py
xploitv-0.1.1.dist-info/LICENSE
xploitv-0.1.1.dist-info/METADATA
xploitv-0.1.1.dist-info/WHEEL
xploitv-0.1.1.dist-info/entry_points.txt
xploitv-0.1.1.dist-info/top_level.txt
xploitv-0.1.1.dist-info/zip-safe
xploitv-0.1.1.dist-info/RECORD
