Metadata-Version: 2.1
Name: xploitv
Version: 0.1.1
Summary: An automated Xploitv grabber
Home-page: https://fsundays.tech/
Author: Kike Fontan (@CosasDePuma)
Author-email: kikefontanlorenzo@gmail.com
License: WTFPL
Project-URL: Bug Tracker, https://www.github.com/cosasdepuma/XPLOITV/issues
Project-URL: Documentation, https://www.github.com/cosasdepuma/XPLOITV
Project-URL: Source Code, https://www.github.com/cosasdepuma/XPLOITV
Keywords: xploitv facebook grabber hacking
Platform: any
Classifier: Environment :: Console
Classifier: License :: Free For Educational Use
Classifier: Natural Language :: English
Classifier: Programming Language :: Python :: 3
Classifier: Programming Language :: Python :: 3.8
Classifier: Programming Language :: Python :: 3 :: Only
Classifier: Programming Language :: Python :: Implementation :: PyPy
Classifier: Topic :: Education :: Testing
Classifier: Topic :: Games/Entertainment
Classifier: Topic :: Internet
Classifier: Topic :: Scientific/Engineering :: Information Analysis
Classifier: Topic :: Security
Classifier: Topic :: Utilities
Requires-Python: >=3.8
